fairdatanow/__init__.py
fairdatanow/_modidx.py
fairdatanow/paramviewer.py
fairdatanow-0.2.12.dist-info/licenses/LICENSE
fairdatanow-0.2.12.dist-info/METADATA
fairdatanow-0.2.12.dist-info/WHEEL
fairdatanow-0.2.12.dist-info/entry_points.txt
fairdatanow-0.2.12.dist-info/top_level.txt
fairdatanow-0.2.12.dist-info/RECORD
