Metadata-Version: 2.4
Name: fairdatanow
Version: 0.2.12
Summary: Experimental Python package to support working with data from (y)our Nextcloud server
Home-page: https://github.com/fligt/fairdatanow
Author: Frank Ligterink
Author-email: frank.ligterink@gmail.com
License: MIT License
Keywords: nbdev jupyter notebook python
Classifier: Development Status :: 4 - Beta
Classifier: Intended Audience :: Developers
Classifier: Natural Language :: English
Classifier: Programming Language :: Python :: 3.7
Classifier: Programming Language :: Python :: 3.8
Classifier: Programming Language :: Python :: 3.9
Classifier: Programming Language :: Python :: 3.10
Classifier: Programming Language :: Python :: 3.11
Classifier: Programming Language :: Python :: 3.12
Classifier: License :: OSI Approved :: MIT License
Requires-Python: >=3.7
License-File: LICENSE
Requires-Dist: nc-py-api
Requires-Dist: humanize
Requires-Dist: panel
Requires-Dist: param
Requires-Dist: pandas
Requires-Dist: IPython
Requires-Dist: ipynb-path
Requires-Dist: matplotlib
Provides-Extra: dev
Dynamic: author
Dynamic: author-email
Dynamic: classifier
Dynamic: description
Dynamic: description-content-type
Dynamic: home-page
Dynamic: keywords
Dynamic: license
Dynamic: license-file
Dynamic: provides-extra
Dynamic: requires-dist
Dynamic: requires-python
Dynamic: summary
